{
  "sections": {
    "a7278f70-4e30-4842-a597-b42daa02c6fc": {
      "type": "image--image",
      "settings": {
        "image": "shopify:\/\/shop_images\/Assouline-OGimage-1-1024x538.png",
        "parallax": true,
        "alignment": "center",
        "hero_size": "medium",
        "text-over-image-width": "full-width"
      }
    },
    "caa04637-6009-4065-89c7-931d3e44b826": {
      "type": "text--rich-text",
      "settings": {
        "colors": "white",
        "width": "medium",
        "subheading": "",
        "page_title": "",
        "title": "Meet Alexandre Assouline, Assouline Publishing, New-York",
        "text": "<p>Alexandre Assouline, 28, is a creative library designer at his family’s luxury publishing company: Assouline. The aim of their travel books is to show the essence of a  destination, evoking emotions, and providing insider informations. We sit down with the young fogey to hear more about his perfect library, his favourite object, his interior design taste, and why he never thought of bringing something home from a hotel.<\/p>",
        "button_link": "",
        "button_label": ""
      }
    },
    "60bed94f-19d1-471f-9213-301734a4bab2": {
      "type": "text--image-with-text",
      "settings": {
        "colors": "white",
        "image-width": "extra-large",
        "image": "shopify:\/\/shop_images\/AssoulineCover-731x1024.jpg",
        "layout": "right",
        "subheading": "",
        "location": false,
        "title": "",
        "text_block": "<p><strong>How would you define Assouline’s sensibility?<br\/><\/strong>Having always proudly stood for luxury and culture, we are dedicated to inspiring through the pages of our titles while evoking emotions and providing information. In essence, we fully embrace the importance of a lifestyle devoted to the celebration of the very best in culture.<\/p><p><strong>How does a location make it on the Assouline Travel list?<br\/><\/strong>As a company today, we carefully select each location based on what we know and love. Familiarity to the subject is always a must. We travel to the places we cover and in turn, our goal is to make our audience discover it through our lens. To further enhance our works, we make it a priority to select some of the best, most notable authors for whichever specialized area we have at hand.<\/p>",
        "page_description": false,
        "button_link": "",
        "hotel_page_url": false,
        "button_label": ""
      }
    },
    "35b16fa5-38a0-4a0d-b186-e6266af128fc": {
      "type": "text--image-with-text",
      "settings": {
        "colors": "white",
        "image-width": "extra-large",
        "image": "shopify:\/\/shop_images\/2-3.png",
        "layout": "right",
        "subheading": "",
        "location": false,
        "title": "2. Cornerstone",
        "text_block": "<p>3 Prince Edward Rd, E9 5NP<br\/><strong>Head chef:<\/strong> James Toth<br\/><strong>Order the:<\/strong> Pickled oysters<br\/><br\/><\/p><p>If something low-key but nevertheless delicious is more your style, then Tom Brown’s solo debut, Cornerstone, should be your first point of call. His produce-driven approach sees seafood as the star of the show, while a seat at the bar offers an unparalleled view of the chefs at work.<\/p>",
        "page_description": false,
        "button_link": "https:\/\/cornerstonehackney.com\/",
        "hotel_page_url": false,
        "button_label": "Book Now"
      }
    },
    "main": {
      "type": "template--article",
      "disabled": true,
      "settings": {
        "show_author_name": false,
        "show_dates": true,
        "blog-sidebar-link": "",
        "blog_sidebar_title": "",
        "blog_sidebar_desc": "",
        "show_blog_tags": false,
        "show_recent_posts": false
      }
    },
    "blog-posts": {
      "type": "blog--blog-posts",
      "settings": {
        "colors": "light",
        "subheading": "BLOG",
        "title": "Latest articles",
        "post_limit": 3,
        "show_author_name": false,
        "show_dates": true,
        "show_blog_images": true,
        "imageSize": "square"
      }
    }
  },
  "order": [
    "a7278f70-4e30-4842-a597-b42daa02c6fc",
    "caa04637-6009-4065-89c7-931d3e44b826",
    "60bed94f-19d1-471f-9213-301734a4bab2",
    "35b16fa5-38a0-4a0d-b186-e6266af128fc",
    "main",
    "blog-posts"
  ]
}
