{
  "sections": {
    "a7278f70-4e30-4842-a597-b42daa02c6fc": {
      "type": "image--image",
      "settings": {
        "image": "shopify:\/\/shop_images\/g-19-circulo-mexicano-1024x601.jpg",
        "parallax": true,
        "alignment": "center",
        "hero_size": "medium",
        "text-over-image-width": "full-width"
      }
    },
    "caa04637-6009-4065-89c7-931d3e44b826": {
      "type": "text--rich-text",
      "settings": {
        "colors": "white",
        "width": "medium",
        "subheading": "",
        "page_title": "Meet Carlos Couturier, Co-founder of Grupo Habita",
        "title": "",
        "text": "<p>Carlos Couturier is the “visionary” behind Grupo Habita – the famous Mexican hotel group. With an ability to sense the potential in an idea that is still a seedling, Carlos, alongside his partners, has revolutionized the concept of boutique hotels in Mexico. We sit down to talk about what makes a great hotelier, the signs to identify the next “destination” and his vision.<\/p>",
        "button_link": "",
        "button_label": ""
      }
    },
    "60bed94f-19d1-471f-9213-301734a4bab2": {
      "type": "text--image-with-text",
      "settings": {
        "colors": "white",
        "image-width": "extra-large",
        "image": "shopify:\/\/shop_images\/g-01-circulo-mexicano-1024x601.jpg",
        "layout": "right",
        "subheading": "",
        "location": false,
        "title": "",
        "text_block": "<p><strong>What, in your previous careers, has helped you become great hoteliers?<\/strong><\/p><p>Discipline.<\/p><p><strong>What makes a good hotel?<\/strong><\/p><p>Time.<\/p>",
        "page_description": false,
        "button_link": "",
        "hotel_page_url": false,
        "button_label": ""
      }
    },
    "35b16fa5-38a0-4a0d-b186-e6266af128fc": {
      "type": "text--image-with-text",
      "settings": {
        "colors": "white",
        "image-width": "extra-large",
        "image": "shopify:\/\/shop_images\/g-05-circulo-mexicano-1024x601.jpg",
        "layout": "left",
        "subheading": "",
        "location": false,
        "title": "",
        "text_block": "<p><strong>Are there early signs to know that a location will be the next “destination”?<\/strong><\/p><p>Yes. It starts with word of mouth. A certain ‘crowd‘ arrives early (bohemians, creatives, visionaries). The place must be authentic, fresh, untouched.<\/p><p><strong>Can you tell us about your vision in terms of interior design?<\/strong><\/p><p>Our vision is dynamic. We follow our instincts. We like working with emerging talents in all creative fields (architecture, design, music, food, culture).<\/p><p><strong>Is there a piece in one of your locations that has a special meaning to you?<\/strong><\/p><p>Not really. Every location is special. It is ‘the whole‘ that holds the meaning.<\/p>",
        "page_description": false,
        "button_link": "",
        "hotel_page_url": false,
        "button_label": ""
      }
    },
    "542fedff-77b4-46a5-9979-d244f4e16ff2": {
      "type": "text--image-with-text",
      "settings": {
        "colors": "white",
        "image-width": "extra-large",
        "image": "shopify:\/\/shop_images\/Schermata-2021-06-01-alle-18.00.09-1024x683.png",
        "layout": "right",
        "subheading": "",
        "location": false,
        "title": "",
        "text_block": "<p><strong>What is the biggest lesson you’ve learned since your first project?<\/strong><\/p><p>Consistency.<\/p><p><strong>What has this year changed for you and your vision for Grupo Habita?<\/strong><\/p><p>A better understanding of nature. Of simple life. The real meaning of humility.<\/p>",
        "page_description": false,
        "button_link": "",
        "hotel_page_url": false,
        "button_label": ""
      }
    },
    "7192b16d-694d-402a-93f3-ceba9dac7bc0": {
      "type": "text--image-with-text",
      "settings": {
        "colors": "white",
        "image-width": "extra-large",
        "image": "shopify:\/\/shop_images\/Schermata-2021-06-01-alle-18.01.57-1024x684.png",
        "layout": "left",
        "subheading": "",
        "location": false,
        "title": "",
        "text_block": "<p><strong>What is the biggest lesson you’ve learned since your first project?<\/strong><\/p><p>Consistency.<\/p><p><strong>What has this year changed for you and your vision for Grupo Habita?<\/strong><\/p><p>A better understanding of nature. Of simple life. The real meaning of humility.<\/p>",
        "page_description": false,
        "button_link": "",
        "hotel_page_url": false,
        "button_label": ""
      }
    },
    "7ec9ad06-7edb-4172-ba0c-0d0b0ff9adc1": {
      "type": "image--gallery",
      "blocks": {
        "template--17937602707771__7ec9ad06-7edb-4172-ba0c-0d0b0ff9adc1-1675957496cf23f6b2-0": {
          "type": "image",
          "settings": {
            "image": "shopify:\/\/shop_images\/High-Wooden-Coat-Rack-1024x1024.jpg",
            "link": "",
            "title": "",
            "description": "<p>High Wooden Coat Rack<\/p><p>£888<\/p>"
          }
        },
        "template--17937602707771__7ec9ad06-7edb-4172-ba0c-0d0b0ff9adc1-1675957496cf23f6b2-1": {
          "type": "image",
          "settings": {
            "image": "shopify:\/\/shop_images\/Set-of-1784-Collection-Wooden-Chair-and-Stool-1024x1024.jpg",
            "link": "",
            "title": "",
            "description": "<p>1784 Collection Wooden Stool<\/p><p>£533<\/p>"
          }
        },
        "template--17937602707771__7ec9ad06-7edb-4172-ba0c-0d0b0ff9adc1-1675957496cf23f6b2-2": {
          "type": "image",
          "settings": {
            "image": "shopify:\/\/shop_images\/1784-Wooden-Chair-with-Polypropylene-Fabric-1024x1024.jpg",
            "link": "",
            "title": "",
            "description": "<p>1784 Wooden Chair with Polypropylene Fabric<\/p><p>£641<\/p>"
          }
        }
      },
      "block_order": [
        "template--17937602707771__7ec9ad06-7edb-4172-ba0c-0d0b0ff9adc1-1675957496cf23f6b2-0",
        "template--17937602707771__7ec9ad06-7edb-4172-ba0c-0d0b0ff9adc1-1675957496cf23f6b2-1",
        "template--17937602707771__7ec9ad06-7edb-4172-ba0c-0d0b0ff9adc1-1675957496cf23f6b2-2"
      ],
      "settings": {
        "colors": "white",
        "subheading": "",
        "title": ""
      }
    },
    "main": {
      "type": "template--article",
      "disabled": true,
      "settings": {
        "show_author_name": false,
        "show_dates": true,
        "blog-sidebar-link": "",
        "blog_sidebar_title": "",
        "blog_sidebar_desc": "",
        "show_blog_tags": false,
        "show_recent_posts": false
      }
    },
    "blog-posts": {
      "type": "blog--blog-posts",
      "settings": {
        "colors": "light",
        "subheading": "BLOG",
        "title": "Latest articles",
        "post_limit": 3,
        "show_author_name": false,
        "show_dates": true,
        "show_blog_images": true,
        "imageSize": "square"
      }
    }
  },
  "order": [
    "a7278f70-4e30-4842-a597-b42daa02c6fc",
    "caa04637-6009-4065-89c7-931d3e44b826",
    "60bed94f-19d1-471f-9213-301734a4bab2",
    "35b16fa5-38a0-4a0d-b186-e6266af128fc",
    "542fedff-77b4-46a5-9979-d244f4e16ff2",
    "7192b16d-694d-402a-93f3-ceba9dac7bc0",
    "7ec9ad06-7edb-4172-ba0c-0d0b0ff9adc1",
    "main",
    "blog-posts"
  ]
}
